entropy_framework
