Metadata-Version: 1.0
Name: entropy-framework
Version: 0.0.3
Summary: Entity-Registry-Process framework
Home-page: https://github.com/aliskhakov/entropy_framework
Author: Albert Iskhakov
Author-email: aliskhakov@gmail.com
License: Apache License 2.0
Platform: UNKNOWN
